django_quill/__init__.py
django_quill/config.py
django_quill/fields.py
django_quill/forms.py
django_quill/quill.py
django_quill/widgets.py
django_quill/drf/__init__.py
django_quill/drf/fields.py
django_quill/management/__init__.py
django_quill/management/commands/__init__.py
django_quill/management/commands/convert_to_quill.py
django_quill/static/django_quill/django_quill.css
django_quill/static/django_quill/django_quill.js
django_quill/templates/django_quill/media.html
django_quill/templates/django_quill/widget.html
playground/__init__.py
playground/manage.py
playground/config/__init__.py
playground/config/admin.py
playground/config/apps.py
playground/config/asgi.py
playground/config/backends.py
playground/config/baker.py
playground/config/settings.py
playground/config/urls.py
playground/config/views.py
playground/config/wsgi.py
playground/django_quill/__init__.py
playground/django_quill/config.py
playground/django_quill/fields.py
playground/django_quill/forms.py
playground/django_quill/quill.py
playground/django_quill/widgets.py
playground/django_quill/drf/__init__.py
playground/django_quill/drf/fields.py
playground/django_quill/management/__init__.py
playground/django_quill/management/commands/__init__.py
playground/django_quill/management/commands/convert_to_quill.py
playground/posts/__init__.py
playground/posts/admin.py
playground/posts/apis.py
playground/posts/apps.py
playground/posts/forms.py
playground/posts/models.py
playground/posts/serializers.py
playground/posts/signals.py
playground/posts/tests.py
playground/posts/urls.py
playground/posts/views.py
playground/posts/migrations/0001_initial.py
playground/posts/migrations/0002_nonquillpost.py
playground/posts/migrations/__init__.py
django_quill_editor-0.1.41.dist-info/LICENSE
django_quill_editor-0.1.41.dist-info/METADATA
django_quill_editor-0.1.41.dist-info/WHEEL
django_quill_editor-0.1.41.dist-info/top_level.txt
django_quill_editor-0.1.41.dist-info/zip-safe
django_quill_editor-0.1.41.dist-info/RECORD
