Metadata-Version: 2.1
Name: django-quill-editor
Version: 0.1.41
Summary: Integrate Quill editor with Django project.
Home-page: https://github.com/LeeHanYeong/django-quill-editor
Author: lhy
Author-email: dev@lhy.kr
License: MIT
Classifier: Framework :: Django
Classifier: Framework :: Django :: 4.2
Classifier: Programming Language :: Python
Classifier: Programming Language :: Python :: 3.8
Classifier: Programming Language :: Python :: 3.9
Classifier: Programming Language :: Python :: 3.10
Classifier: Programming Language :: Python :: 3.11
Classifier: Programming Language :: Python :: 3.12
Classifier: Development Status :: 4 - Beta
Requires-Python: >3.8
License-File: LICENSE
Requires-Dist: django>=3.2
